goad/__init__.py
goad-0.0.0.dist-info/METADATA
goad-0.0.0.dist-info/WHEEL
goad-0.0.0.dist-info/top_level.txt
goad-0.0.0.dist-info/RECORD
