Metadata-Version: 2.1
Name: goad
Version: 0.0.0
Summary: Coming soon
Author-email: Mayfly <mayfly277@gmail.com>
